dagon/__init__.py
dagon/batch.py
dagon/config.py
dagon/dag_tps.py
dagon/docker_task.py
dagon/remote.py
dagon/task.py
dagon/api/__init__.py
dagon/api/server.py
dagon/cloud/__init__.py
dagon/communication/__init__.py
dagon/communication/data_transfer.py
dagon/communication/scp.py
dagon/communication/ssh.py
dagon/dockercontainer/__init__.py
dagon/ftp_publisher/__init__.py
dagonstar-1.0.2.dist-info/LICENSE
dagonstar-1.0.2.dist-info/METADATA
dagonstar-1.0.2.dist-info/WHEEL
dagonstar-1.0.2.dist-info/top_level.txt
dagonstar-1.0.2.dist-info/RECORD
