Metadata-Version: 2.1
Name: dagonstar
Version: 1.0.2
Summary: DAGon* is a simple Python based workflow engine able to run job on everything from the local machine to distributed virtual HPC clusters hosted in private and public clouds.
Home-page: https://github.com/DagOnStar/dagonstar
Author: Raffaele Montella
Author-email: raffaele.montella@uniparthenope.it
License: Apache 2.0
Classifier: Programming Language :: Python :: 3
Classifier: Operating System :: OS Independent
Requires-Python: >=3.8.15
License-File: LICENSE
Requires-Dist: requests ==2.31.0
Requires-Dist: fabric3
Requires-Dist: boto3 ==1.28.62
Requires-Dist: paramiko
Requires-Dist: graphviz ==0.20.1
Requires-Dist: globus-sdk ==3.28.0
Requires-Dist: docker ==6.1.3
Requires-Dist: apache-libcloud ==3.8.0
Requires-Dist: configparser ==6.0.0
Requires-Dist: flask ==2.2.2
Requires-Dist: Flask-API ==3.1
Requires-Dist: pycrypto ==2.6.1
Requires-Dist: werkzeug ==2.2.2
Requires-Dist: pycryptodome ==3.20.0
